anomaly_detector/__init__.py
anomaly_detector/base.py
anomaly_detector/common/__init__.py
anomaly_detector/common/constants.py
anomaly_detector/common/data_processor.py
anomaly_detector/common/error_code.py
anomaly_detector/common/exception.py
anomaly_detector/common/time_util.py
anomaly_detector/multivariate/__init__.py
anomaly_detector/multivariate/contract.py
anomaly_detector/multivariate/dataset.py
anomaly_detector/multivariate/model.py
anomaly_detector/multivariate/module.py
anomaly_detector/multivariate/util.py
anomaly_detector/univariate/__init__.py
anomaly_detector/univariate/_anomaly_kernel_cython.c
anomaly_detector/univariate/_anomaly_kernel_cython.cp312-win_amd64.pyd
anomaly_detector/univariate/_anomaly_kernel_cython.pyx
anomaly_detector/univariate/univariate_anomaly_detection.py
anomaly_detector/univariate/detectors/__init__.py
anomaly_detector/univariate/detectors/detector.py
anomaly_detector/univariate/detectors/dynamic_filter.py
anomaly_detector/univariate/detectors/esd_filter.py
anomaly_detector/univariate/detectors/spectral_residual.py
anomaly_detector/univariate/detectors/z_score.py
anomaly_detector/univariate/filling_up/__init__.py
anomaly_detector/univariate/filling_up/fill_up.py
anomaly_detector/univariate/filling_up/fill_up_methods.py
anomaly_detector/univariate/model/__init__.py
anomaly_detector/univariate/model/detect.py
anomaly_detector/univariate/model/detect_model.py
anomaly_detector/univariate/model/dynamic_threshold.py
anomaly_detector/univariate/model/hbos_detection.py
anomaly_detector/univariate/model/seasonal_series.py
anomaly_detector/univariate/model/series_compete_processor.py
anomaly_detector/univariate/model/spectral_residual_model.py
anomaly_detector/univariate/period/__init__.py
anomaly_detector/univariate/period/period_detect.py
anomaly_detector/univariate/period/simple.py
anomaly_detector/univariate/period/spectrum.py
anomaly_detector/univariate/resource/__init__.py
anomaly_detector/univariate/resource/error_message.py
time_series_anomaly_detector-0.3.7.dist-info/licenses/LICENSE
time_series_anomaly_detector-0.3.7.dist-info/METADATA
time_series_anomaly_detector-0.3.7.dist-info/WHEEL
time_series_anomaly_detector-0.3.7.dist-info/top_level.txt
time_series_anomaly_detector-0.3.7.dist-info/RECORD
