Metadata-Version: 2.4
Name: time-series-anomaly-detector
Version: 0.3.7
Summary: Time Series Anomaly Detector
Author-email: Microsoft Corporation <ad-oss@microsoft.com>
Maintainer-email: Microsoft Corporation <ad-oss@microsoft.com>
License:     MIT License
Project-URL: Homepage, https://github.com/microsoft/anomaly-detector
Keywords: machine learning,time series,anomaly detection
Classifier: Development Status :: 4 - Beta
Classifier: Intended Audience :: Developers
Classifier: Topic :: Scientific/Engineering :: Artificial Intelligence
Classifier: License :: OSI Approved :: MIT License
Classifier: Programming Language :: Python :: 3.10
Classifier: Programming Language :: Python :: 3.11
Classifier: Programming Language :: Python :: 3.12
Requires-Python: >=3.10.0
License-File: LICENSE
Requires-Dist: numpy<2,>=1.23.5
Requires-Dist: pandas<=2.2.3,>=1.3.5
Requires-Dist: seasonal>=0.3.1
Requires-Dist: scipy<1.13.0,>=1.9.3
Requires-Dist: pytz>=2018.9
Requires-Dist: rstl>=0.1.3
Requires-Dist: psutil>=6.1.1
Requires-Dist: statsmodels>=0.14.1
Requires-Dist: scikit-learn>=1.3.2
Requires-Dist: arch>=6.3.0
Requires-Dist: torch>=1.13.1
Requires-Dist: tqdm>=4.66.1
Requires-Dist: mlflow<4.0,>=3.1.0
Requires-Dist: pytest>=7.4.4
Dynamic: license-file
